w2nvshellmsg/__init__.py
w2nvshellmsg/main.py
W2NVShellMessage-0.1.5.dist-info/LICENSE
W2NVShellMessage-0.1.5.dist-info/METADATA
W2NVShellMessage-0.1.5.dist-info/WHEEL
W2NVShellMessage-0.1.5.dist-info/entry_points.txt
W2NVShellMessage-0.1.5.dist-info/top_level.txt
W2NVShellMessage-0.1.5.dist-info/RECORD
