Metadata-Version: 2.1
Name: W2NVShellMessage
Version: 0.1.5
Summary: A package to display quotes from "Welcome to Night Vale" whenever a new terminal window is launched
Home-page: https://github.com/rijumone/W2NVShellMessage
Author: Rijumone Choudhuri
Author-email: mailmeonriju@gmail.com
License: MIT
Project-URL: Bug Tracker, https://github.com/rijumone/W2NVShellMessage/issues
Platform: UNKNOWN
Requires-Python: >=3.6
License-File: LICENSE
Requires-Dist: pytest
Requires-Dist: requests
Requires-Dist: loguru
Requires-Dist: bs4
Requires-Dist: colorama
